{"status":"done","publicPath":"/","chunks":{"javascripts":[{"name":"javascripts.bundle.js","publicPath":"/javascripts.bundle.js","path":"/Users/irinazigalova/animation_django/public/javascripts/javascripts.bundle.js"},{"name":"0.88efc303ea7142c8a897.hot-update.js","publicPath":"/0.88efc303ea7142c8a897.hot-update.js","path":"/Users/irinazigalova/animation_django/public/javascripts/0.88efc303ea7142c8a897.hot-update.js"}],"styles":[{"name":"styles.bundle.js","publicPath":"/styles.bundle.js","path":"/Users/irinazigalova/animation_django/public/javascripts/styles.bundle.js"}]},"error":"ModuleBuildError","message":"Module build failed: SyntaxError: Unexpected token (1:15)\n\n> 1 | export default const getLastShorts = () => (dispatch) => {\n    |                ^\n  2 |   dispatch({\n  3 |     type: 'FETCH_LASTSHORTS_ONLOAD'\n  4 |   })\n"}